.gitignore
AUTHORS.txt
CHANGES.rst
CLASSIFIERS.txt
LICENSE
MANIFEST.in
README.rst
REQUIREMENTS.txt
setup.py
myterm/__init__.py
myterm/color.py
myterm/config.py
myterm/log.py
myterm/parser.py
myterm/startup.py
myterm/table.py
myterm/util.py
myterm.egg-info/PKG-INFO
myterm.egg-info/SOURCES.txt
myterm.egg-info/dependency_links.txt
myterm.egg-info/requires.txt
myterm.egg-info/top_level.txt
myterm/__pycache__/__init__.cpython-34.pyc
sample/conf.py
sample/confwrong.py
sample/test1.py
sample/test2.py
sample/test3.py
sample/test4.py